datatypes.py
audio_processing-0.0.1.dist-info/LICENSE.txt
audio_processing-0.0.1.dist-info/METADATA
audio_processing-0.0.1.dist-info/WHEEL
audio_processing-0.0.1.dist-info/top_level.txt
audio_processing-0.0.1.dist-info/RECORD
